llm_cgr/__init__.py
llm_cgr/decorators.py
llm_cgr/defaults.py
llm_cgr/enums.py
llm_cgr/json_utils.py
llm_cgr/py.typed
llm_cgr/timeout.py
llm_cgr/analyse/__init__.py
llm_cgr/analyse/classes.py
llm_cgr/analyse/regexes.py
llm_cgr/analyse/languages/__init__.py
llm_cgr/analyse/languages/code_data.py
llm_cgr/analyse/languages/javascript.py
llm_cgr/analyse/languages/python.py
llm_cgr/llm/__init__.py
llm_cgr/llm/generate.py
llm_cgr/llm/prompts.py
llm_cgr/llm/clients/__init__.py
llm_cgr/llm/clients/anthropic.py
llm_cgr/llm/clients/base.py
llm_cgr/llm/clients/deepseek.py
llm_cgr/llm/clients/mistral.py
llm_cgr/llm/clients/nscale.py
llm_cgr/llm/clients/openai.py
llm_cgr/llm/clients/protocol.py
llm_cgr/llm/clients/together.py
llm_cgr/scripts/test_cuda.py
llm_codegen_research-2.6.dist-info/licenses/LICENSE
llm_codegen_research-2.6.dist-info/METADATA
llm_codegen_research-2.6.dist-info/WHEEL
llm_codegen_research-2.6.dist-info/entry_points.txt
llm_codegen_research-2.6.dist-info/top_level.txt
llm_codegen_research-2.6.dist-info/RECORD
