Metadata-Version: 2.4
Name: llm-codegen-research
Version: 2.6
Summary: Useful classes and methods for researching code-generation by LLMs.
Author-email: Lukas Twist <itsluketwist@gmail.com>
Project-URL: Homepage, https://github.com/itsluketwist/llm-codegen-research
Keywords: llm,code-generation,research,prompting,nlp
Classifier: Programming Language :: Python
Classifier: Programming Language :: Python :: 3
Requires-Python: >=3.11
License-File: LICENSE
Requires-Dist: anthropic
Requires-Dist: esprima
Requires-Dist: genbadge[coverage]
Requires-Dist: mistralai
Requires-Dist: openai
Requires-Dist: together
Dynamic: license-file
